{
  "success": true,
  "msg": "",
  "data": [
    {
      "name": "老小区管理差",
      "value": "5"
    },
    {
      "name": "办事效率低",
      "value": "4"
    },
    {
      "name": "爱理不理",
      "value": "3"
    },
    {
      "name": "老小区停车难",
      "value": "2"
    },
    {
      "name": "处理不及时",
      "value": "1"
    },
    {
      "name": "手续繁琐",
      "value": "5"
    },
    {
      "name": "噪音大",
      "value": "4"
    },
    {
      "name": "拖拖拉拉",
      "value": "3"
    },
    {
      "name": "拥堵严重",
      "value": "2"
    },
    {
      "name": "看守所",
      "value": "1"
    }
  ],
  "data1": [
    {
      "name": "老小区管理差",
      "value": "5"
    },
    {
      "name": "办事效率低",
      "value": "4"
    },
    {
      "name": "爱理不理",
      "value": "3"
    },
    {
      "name": "老小区停车难",
      "value": "2"
    },
    {
      "name": "处理不及时",
      "value": "1"
    },
    {
      "name": "手续繁琐",
      "value": "5"
    },
    {
      "name": "噪音大",
      "value": "4"
    },
    {
      "name": "拖拖拉拉",
      "value": "3"
    },
    {
      "name": "拥堵严重",
      "value": "2"
    },
    {
      "name": "看守所",
      "value": "1"
    }
  ],
  "data2": [
    {"name": "老小区管理差", "value": "5"},
    {"name": "办事效率低", "value": "4"},
    {"name": "爱理不理", "value": "3"},
    {"name": "老小区停车难", "value": "2"},
    {"name": "处理不及时", "value": "1"},
    {"name": "手续繁琐", "value": "5"},
    {"name": "噪音大", "value": "4"},
    {"name": "拖拖拉拉", "value": "3"},
    {"name": "拥堵严重", "value": "2"},
    {"name": "看守所", "value": "1"}
  ]
}